cuclasses/CallableDict.py
cuclasses/DottableDict.py
cuclasses/HeaderCopy.py
cuclasses/NumGetDict.py
cuclasses/SingletonDecoration.py
cuclasses/StrKeyDict.py
cuclasses/TimeCount.py
cuclasses/TimePrint.py
cuclasses/__init__.py
cuclasses/__main__.py
cuclasses-0.0.3.dist-info/LICENSE
cuclasses-0.0.3.dist-info/METADATA
cuclasses-0.0.3.dist-info/WHEEL
cuclasses-0.0.3.dist-info/top_level.txt
cuclasses-0.0.3.dist-info/RECORD
