Metadata-Version: 2.1
Name: cuclasses
Version: 0.0.3
Summary: useful classes
Home-page: https://github.com/HHHHhgqcdxhg/cuclasses
Author: HHHHhg
Author-email: 2894700792@qq.com
License: UNKNOWN
Platform: UNKNOWN
Classifier: Natural Language :: Chinese (Simplified)
